zfapi/__init__.py
zfapi/config.py
zfapi/api/__init__.py
zfapi/api/get_info.py
zfapi/api/login.py
zfapi-0.0.1.dist-info/LICENSE
zfapi-0.0.1.dist-info/METADATA
zfapi-0.0.1.dist-info/WHEEL
zfapi-0.0.1.dist-info/top_level.txt
zfapi-0.0.1.dist-info/RECORD
