Metadata-Version: 2.1
Name: zfapi
Version: 0.0.1
Summary: 正方教务管理系统API
Home-page: https://srpihot.github.io/zfapi/
Author: Srpihot
Author-email: srpihot@foxmail.com
License: UNKNOWN
Platform: UNKNOWN
Classifier: Intended Audience :: Developers
Classifier: License :: OSI Approved :: MIT License
Classifier: Programming Language :: Python :: 3
Classifier: Programming Language :: Python :: 3.4
Classifier: Programming Language :: Python :: 3.5
Classifier: Programming Language :: Python :: 3.6
Classifier: Programming Language :: Python :: 3.7
Classifier: Programming Language :: Python :: 3.8
Requires-Python: >=3.0.0
Requires-Dist: requests
Requires-Dist: bs4
Requires-Dist: rsa
Requires-Dist: Crypto
